{
	"class" : {
		 },
	"instance" : {
		"add" : "ShoYoshida 7/18/2015 10:01",
		"add:" : "ShoYoshida 7/18/2015 10:05",
		"addAll:" : "ShoYoshida 7/15/2015 01:01",
		"count" : "ShoYoshida 7/18/2015 09:58",
		"data:" : "ShoYoshida 7/15/2015 00:59",
		"datum:" : "ShoYoshida 7/15/2015 01:00",
		"defaultAPI" : "ShoYoshida 7/14/2015 13:04",
		"delete" : "ShoYoshida 7/18/2015 10:01",
		"email:" : "ShoYoshida 7/15/2015 01:04",
		"emails:" : "ShoYoshida 7/15/2015 10:57",
		"get" : "ShoYoshida 7/18/2015 09:56",
		"url" : "ShoYoshida 7/14/2015 13:05" } }
